msg2apps.py
msg2apps-1.1.0.dist-info/METADATA
msg2apps-1.1.0.dist-info/WHEEL
msg2apps-1.1.0.dist-info/top_level.txt
msg2apps-1.1.0.dist-info/RECORD
