Metadata-Version: 2.1
Name: msg2apps
Version: 1.1.0
Summary: A module for sending messages to communication apps
Home-page: https://github.com/daksim/msg2apps
Author: Daksimz
Author-email: daksimzhang@gmail.com
License: MIT
Platform: UNKNOWN
Requires: requests
Requires: json
